LICENSE
MANIFEST.in
README.md
requirements.txt
setup.py
airtest_selenium/__init__.py
airtest_selenium/exceptions.py
airtest_selenium/proxy.py
airtest_selenium/report.py
airtest_selenium.egg-info/PKG-INFO
airtest_selenium.egg-info/SOURCES.txt
airtest_selenium.egg-info/dependency_links.txt
airtest_selenium.egg-info/requires.txt
airtest_selenium.egg-info/top_level.txt
airtest_selenium/utils/__init__.py
airtest_selenium/utils/airtest_api.py
airtest_selenium/utils/six.py