Metadata-Version: 1.0
Name: airtest-selenium
Version: 1.0.6
Summary: Selenium with airtest test framework.
Home-page: https://github.com/AirtestProject/airtest-selenium
Author: Netease Games
Author-email: rockywhisper@163.com
License: Apache License 2.0
Keywords: selenium,automation test,web ui automation
Platform: UNKNOWN
